<annotation>
	<folder>JPEGImages</folder>
	<filename>054_1_0073.png</filename>
	<path>C:\Users\14531\Desktop\VOC2007\JPEGImages\054_1_0073.png</path>
	<source>
		<database>Unknown</database>
	</source>
	<size>
		<width>105</width>
		<height>95</height>
		<depth>3</depth>
	</size>
	<segmented>0</segmented>
	<object>
		<name>Whole_section</name>
		<pose>Unspecified</pose>
		<truncated>0</truncated>
		<difficult>0</difficult>
		<bndbox>
			<xmin>24</xmin>
			<ymin>15</ymin>
			<xmax>85</xmax>
			<ymax>78</ymax>
		</bndbox>
	</object>
</annotation>
