<annotation>
	<folder>JPEGImages</folder>
	<filename>054_0094.png</filename>
	<path>C:\Users\14531\Desktop\VOC2007\JPEGImages\054_0094.png</path>
	<source>
		<database>Unknown</database>
	</source>
	<size>
		<width>167</width>
		<height>152</height>
		<depth>3</depth>
	</size>
	<segmented>0</segmented>
	<object>
		<name>Whole_section</name>
		<pose>Unspecified</pose>
		<truncated>0</truncated>
		<difficult>0</difficult>
		<bndbox>
			<xmin>27</xmin>
			<ymin>24</ymin>
			<xmax>140</xmax>
			<ymax>136</ymax>
		</bndbox>
	</object>
</annotation>
